track/application/__init__.py
track/application/cli.py
track/application/core/__init__.py
track/application/core/active_applications.py
track/application/core/common.py
track/application/core/desktop_usage_info/__init__.py
track/application/core/desktop_usage_info/backend_windows/__init__.py
track/application/core/desktop_usage_info/backend_windows/applicationinfo.py
track/application/core/desktop_usage_info/backend_windows/idle.py
track/application/core/desktop_usage_info/backend_x11/__init__.py
track/application/core/desktop_usage_info/backend_x11/applicationinfo.py
track/application/core/desktop_usage_info/backend_x11/idle.py
track/application/core/errors.py
track/application/core/time_tracker.py
track/application/core/util.py
track/application/server/__init__.py
track/application/ui/__init__.py
track/application/ui/active_applications_qtmodel.py
track/application/ui/mainwindow.py
track/application/ui/mainwindow.ui
track/application/ui/qreordertableview.py
track/application/ui/qspoiler.py
track/application/ui/qt_common.py
track/application/ui/rules_model_qt.py
track/application/ui/time_tracker_qt.py
track/application/ui/timegraph.py
python_time_track-0.0.1.dist-info/LICENSE
python_time_track-0.0.1.dist-info/METADATA
python_time_track-0.0.1.dist-info/WHEEL
python_time_track-0.0.1.dist-info/entry_points.txt
python_time_track-0.0.1.dist-info/RECORD
