Metadata-Version: 2.1
Name: python-time-track
Version: 0.0.1
Summary: Automatic Time Tracker
Home-page: https://projects.om-office.de/frans/track.git
Author: Frans Fürst
Author-email: frans.fuerst+gitlab@protonmail.com
Requires-Python: >=3.9,<3.12
Classifier: Programming Language :: Python :: 3
Classifier: Programming Language :: Python :: 3.9
Classifier: Programming Language :: Python :: 3.10
Classifier: Programming Language :: Python :: 3.11
Project-URL: Repository, https://projects.om-office.de/frans/track.git
